{
  "total": 197,
  "public": {
    "count": 126,
    "results": [
      {
        "city": "Bolu",
        "hero": "",
        "name": "Abant İzzet Baysal Üniversitesi",
        "hero_thumbnail": "",
        "slug": "abant-izzet-baysal-universitesi",
        "university_id": "5066549580791808",
        "is_favourited": false,
        "is_private": false,
        "media_url": "https://storage.googleapis.com/university-images-prod/"
      },
      {
        "city": "Kayseri",
        "hero": "",
        "name": "Abdullah Gül Üniversitesi",
        "hero_thumbnail": "",
        "slug": "abdullah-gul-universitesi",
        "university_id": "4785074604081152",
        "is_favourited": false,
        "is_private": false,
        "media_url": "https://storage.googleapis.com/university-images-prod/"
      },
      {
        "city": "Adana",
        "hero": "",
        "name": "Adana Bilim Ve Teknoloji Üniversitesi",
        "hero_thumbnail": "",
        "slug": "adana-bilim-ve-teknoloji-universitesi",
        "university_id": "4644337115725824",
        "is_favourited": false,
        "is_private": false,
        "media_url": "https://storage.googleapis.com/university-images-prod/"
      },
      {
        "city": "Aydın",
        "hero": "",
        "name": "Adnan Menderes Üniversitesi",
        "hero_thumbnail": "",
        "slug": "adnan-menderes-universitesi",
        "university_id": "4925812092436480",
        "is_favourited": false,
        "is_private": false,
        "media_url": "https://storage.googleapis.com/university-images-prod/"
      },
      {
        "city": "Adıyaman",
        "hero": "",
        "name": "Adıyaman Üniversitesi",
        "hero_thumbnail": "",
        "slug": "adyaman-universitesi",
        "university_id": "5207287069147136",
        "is_favourited": false,
        "is_private": false,
        "media_url": "https://storage.googleapis.com/university-images-prod/"
      },
      {
        "city": "Afyonkarahisar",
        "hero": "",
        "name": "Afyon Kocatepe Üniversitesi",
        "hero_thumbnail": "",
        "slug": "afyon-kocatepe-universitesi",
        "university_id": "5488762045857792",
        "is_favourited": false,
        "is_private": false,
        "media_url": "https://storage.googleapis.com/university-images-prod/"
      },
      {
        "city": "Ağrı",
        "hero": "",
        "name": "Ağrı İbrahim Çeçen Üniversitesi",
        "hero_thumbnail": "",
        "slug": "agr-ibrahim-cecen-universitesi",
        "university_id": "4573968371548160",
        "is_favourited": false,
        "is_private": false,
        "media_url": "https://storage.googleapis.com/university-images-prod/"
      },
      {
        "city": "Kırşehir",
        "hero": "",
        "name": "Ahi Evran Üniversitesi",
        "hero_thumbnail": "",
        "slug": "ahi-evran-universitesi",
        "university_id": "5136918324969472",
        "is_favourited": false,
        "is_private": false,
        "media_url": "https://storage.googleapis.com/university-images-prod/"
      },
      {
        "city": "Antalya",
        "hero": "",
        "name": "Akdeniz Üniversitesi",
        "hero_thumbnail": "",
        "slug": "akdeniz-universitesi",
        "university_id": "4855443348258816",
        "is_favourited": false,
        "is_private": false,
        "media_url": "https://storage.googleapis.com/university-images-prod/"
      },
      {
        "city": "Aksaray",
        "hero": "",
        "name": "Aksaray Üniversitesi",
        "hero_thumbnail": "",
        "slug": "aksaray-universitesi",
        "university_id": "5418393301680128",
        "is_favourited": false,
        "is_private": false,
        "media_url": "https://storage.googleapis.com/university-images-prod/"
      },
      {
        "city": "Antalya",
        "hero": "",
        "name": "Alanya Alaaddin Keykubat Üniversitesi",
        "hero_thumbnail": "",
        "slug": "alanya-alaaddin-keykubat-universitesi",
        "university_id": "4714705859903488",
        "is_favourited": false,
        "is_private": false,
        "media_url": "https://storage.googleapis.com/university-images-prod/"
      },
      {
        "city": "Amasya",
        "hero": "",
        "name": "Amasya Üniversitesi",
        "hero_thumbnail": "",
        "slug": "amasya-universitesi",
        "university_id": "4996180836614144",
        "is_favourited": false,
        "is_private": false,
        "media_url": "https://storage.googleapis.com/university-images-prod/"
      },
      {
        "city": "Eskişehir",
        "hero": "",
        "name": "Anadolu Üniversitesi",
        "hero_thumbnail": "",
        "slug": "anadolu-universitesi",
        "university_id": "5559130790035456",
        "is_favourited": false,
        "is_private": false,
        "media_url": "https://storage.googleapis.com/university-images-prod/"
      },
      {
        "city": "Ankara",
        "hero": "",
        "name": "Ankara Üniversitesi",
        "hero_thumbnail": "",
        "slug": "ankara-universitesi",
        "university_id": "4538783999459328",
        "is_favourited": false,
        "is_private": false,
        "media_url": "https://storage.googleapis.com/university-images-prod/"
      },
      {
        "city": "Ardahan",
        "hero": "",
        "name": "Ardahan Üniversitesi",
        "hero_thumbnail": "",
        "slug": "ardahan-universitesi",
        "university_id": "5101733952880640",
        "is_favourited": false,
        "is_private": false,
        "media_url": "https://storage.googleapis.com/university-images-prod/"
      },
      {
        "city": "Artvin",
        "hero": "",
        "name": "Artvin Çoruh Üniversitesi",
        "hero_thumbnail": "",
        "slug": "artvin-coruh-universitesi",
        "university_id": "4820258976169984",
        "is_favourited": false,
        "is_private": false,
        "media_url": "https://storage.googleapis.com/university-images-prod/"
      },
      {
        "city": "Erzurum",
        "hero": "",
        "name": "Atatürk Üniversitesi",
        "hero_thumbnail": "",
        "slug": "ataturk-universitesi",
        "university_id": "5383208929591296",
        "is_favourited": false,
        "is_private": false,
        "media_url": "https://storage.googleapis.com/university-images-prod/"
      },
      {
        "city": "Bakü (Azerbaycan)",
        "hero": "",
        "name": "Azerbaycan Devlet İktisat Üniversitesi",
        "hero_thumbnail": "",
        "slug": "azerbaycan-devlet-iktisat-universitesi",
        "university_id": "5361218697035776",
        "is_favourited": false,
        "is_private": false,
        "media_url": "https://storage.googleapis.com/university-images-prod/"
      },
      {
        "city": "Bakü (Azerbaycan)",
        "hero": "",
        "name": "Azerbaycan Devlet Medeniyet Ve İnce Sanat Üniversitesi",
        "hero_thumbnail": "",
        "slug": "azerbaycan-devlet-medeniyet-ve-ince-sanat-universitesi",
        "university_id": "4657531255259136",
        "is_favourited": false,
        "is_private": false,
        "media_url": "https://storage.googleapis.com/university-images-prod/"
      },
      {
        "city": "Bakü (Azerbaycan)",
        "hero": "",
        "name": "Azerbaycan Devlet Pedagoji Üniversitesi",
        "hero_thumbnail": "",
        "slug": "azerbaycan-devlet-pedagoji-universitesi",
        "university_id": "5220481208680448",
        "is_favourited": false,
        "is_private": false,
        "media_url": "https://storage.googleapis.com/university-images-prod/"
      },
      {
        "city": "Bakü (Azerbaycan)",
        "hero": "",
        "name": "Azerbaycan Diller Üniversitesi",
        "hero_thumbnail": "",
        "slug": "azerbaycan-diller-universitesi",
        "university_id": "4798268743614464",
        "is_favourited": false,
        "is_private": false,
        "media_url": "https://storage.googleapis.com/university-images-prod/"
      },
      {
        "city": "Bakü (Azerbaycan)",
        "hero": "",
        "name": "Azerbaycan Mimarlık Ve İnşaat Üniversitesi",
        "hero_thumbnail": "",
        "slug": "azerbaycan-mimarlk-ve-insaat-universitesi",
        "university_id": "4939006231969792",
        "is_favourited": false,
        "is_private": false,
        "media_url": "https://storage.googleapis.com/university-images-prod/"
      },
      {
        "city": "Bakü (Azerbaycan)",
        "hero": "",
        "name": "Azerbaycan Tıp Üniversitesi",
        "hero_thumbnail": "",
        "slug": "azerbaycan-tp-universitesi",
        "university_id": "5501956185391104",
        "is_favourited": false,
        "is_private": false,
        "media_url": "https://storage.googleapis.com/university-images-prod/"
      },
      {
        "city": "Bakü (Azerbaycan)",
        "hero": "",
        "name": "Bakü Devlet Üniversitesi",
        "hero_thumbnail": "",
        "slug": "baku-devlet-universitesi",
        "university_id": "4587162511081472",
        "is_favourited": false,
        "is_private": false,
        "media_url": "https://storage.googleapis.com/university-images-prod/"
      },
      {
        "city": "Bakü (Azerbaycan)",
        "hero": "",
        "name": "Bakü Slavyan Üniversitesi",
        "hero_thumbnail": "",
        "slug": "baku-slavyan-universitesi",
        "university_id": "5150112464502784",
        "is_favourited": false,
        "is_private": false,
        "media_url": "https://storage.googleapis.com/university-images-prod/"
      },
      {
        "city": "Balıkesir",
        "hero": "",
        "name": "Balıkesir Üniversitesi",
        "hero_thumbnail": "",
        "slug": "balkesir-universitesi",
        "university_id": "5523946417946624",
        "is_favourited": false,
        "is_private": false,
        "media_url": "https://storage.googleapis.com/university-images-prod/"
      },
      {
        "city": "Balıkesir",
        "hero": "",
        "name": "Bandırma Onyedi Eylül Üniversitesi",
        "hero_thumbnail": "",
        "slug": "bandrma-onyedi-eylul-universitesi",
        "university_id": "4609152743636992",
        "is_favourited": false,
        "is_private": false,
        "media_url": "https://storage.googleapis.com/university-images-prod/"
      },
      {
        "city": "Bartın",
        "hero": "",
        "name": "Bartın Üniversitesi",
        "hero_thumbnail": "",
        "slug": "bartn-universitesi",
        "university_id": "5172102697058304",
        "is_favourited": false,
        "is_private": false,
        "media_url": "https://storage.googleapis.com/university-images-prod/"
      },
      {
        "city": "Batman",
        "hero": "",
        "name": "Batman Üniversitesi",
        "hero_thumbnail": "",
        "slug": "batman-universitesi",
        "university_id": "5453577673768960",
        "is_favourited": false,
        "is_private": false,
        "media_url": "https://storage.googleapis.com/university-images-prod/"
      },
      {
        "city": "Bayburt",
        "hero": "",
        "name": "Bayburt Üniversitesi",
        "hero_thumbnail": "",
        "slug": "bayburt-universitesi",
        "university_id": "4749890231992320",
        "is_favourited": false,
        "is_private": false,
        "media_url": "https://storage.googleapis.com/university-images-prod/"
      },
      {
        "city": "Bilecik",
        "hero": "",
        "name": "Bilecik Şeyh Edebali Üniversitesi",
        "hero_thumbnail": "",
        "slug": "bilecik-seyh-edebali-universitesi",
        "university_id": "5594315162124288",
        "is_favourited": false,
        "is_private": false,
        "media_url": "https://storage.googleapis.com/university-images-prod/"
      },
      {
        "city": "Bingöl",
        "hero": "",
        "name": "Bingöl Üniversitesi",
        "hero_thumbnail": "",
        "slug": "bingol-universitesi",
        "university_id": "4521191813414912",
        "is_favourited": false,
        "is_private": false,
        "media_url": "https://storage.googleapis.com/university-images-prod/"
      },
      {
        "city": "Bitlis",
        "hero": "",
        "name": "Bitlis Eren Üniversitesi",
        "hero_thumbnail": "",
        "slug": "bitlis-eren-universitesi",
        "university_id": "4802666790125568",
        "is_favourited": false,
        "is_private": false,
        "media_url": "https://storage.googleapis.com/university-images-prod/"
      },
      {
        "city": "İstanbul",
        "hero": "",
        "name": "Boğaziçi Üniversitesi",
        "hero_thumbnail": "",
        "slug": "bogazici-universitesi",
        "university_id": "5365616743546880",
        "is_favourited": false,
        "is_private": false,
        "media_url": "https://storage.googleapis.com/university-images-prod/"
      },
      {
        "city": "Yozgat",
        "hero": "",
        "name": "Bozok Üniversitesi",
        "hero_thumbnail": "",
        "slug": "bozok-universitesi",
        "university_id": "4661929301770240",
        "is_favourited": false,
        "is_private": false,
        "media_url": "https://storage.googleapis.com/university-images-prod/"
      },
      {
        "city": "Zonguldak",
        "hero": "",
        "name": "Bülent Ecevit Üniversitesi",
        "hero_thumbnail": "",
        "slug": "bulent-ecevit-universitesi",
        "university_id": "5224879255191552",
        "is_favourited": false,
        "is_private": false,
        "media_url": "https://storage.googleapis.com/university-images-prod/"
      },
      {
        "city": "Bursa",
        "hero": "",
        "name": "Bursa Teknik Üniversitesi",
        "hero_thumbnail": "",
        "slug": "bursa-teknik-universitesi",
        "university_id": "5506354231902208",
        "is_favourited": false,
        "is_private": false,
        "media_url": "https://storage.googleapis.com/university-images-prod/"
      },
      {
        "city": "Çanakkale",
        "hero": "",
        "name": "Çanakkale Onsekiz Mart Üniversitesi",
        "hero_thumbnail": "",
        "slug": "canakkale-onsekiz-mart-universitesi",
        "university_id": "5154510511013888",
        "is_favourited": false,
        "is_private": false,
        "media_url": "https://storage.googleapis.com/university-images-prod/"
      },
      {
        "city": "Çankırı",
        "hero": "",
        "name": "Çankırı Karatekin Üniversitesi",
        "hero_thumbnail": "",
        "slug": "cankr-karatekin-universitesi",
        "university_id": "4732298045947904",
        "is_favourited": false,
        "is_private": false,
        "media_url": "https://storage.googleapis.com/university-images-prod/"
      },
      {
        "city": "Manisa",
        "hero": "",
        "name": "Celâl Bayar Üniversitesi",
        "hero_thumbnail": "",
        "slug": "celal-bayar-universitesi",
        "university_id": "5295247999369216",
        "is_favourited": false,
        "is_private": false,
        "media_url": "https://storage.googleapis.com/university-images-prod/"
      },
      {
        "city": "Adana",
        "hero": "",
        "name": "Çukurova Üniversitesi",
        "hero_thumbnail": "",
        "slug": "cukurova-universitesi",
        "university_id": "5013773022658560",
        "is_favourited": false,
        "is_private": false,
        "media_url": "https://storage.googleapis.com/university-images-prod/"
      },
      {
        "city": "Sivas",
        "hero": "",
        "name": "Cumhuriyet Üniversitesi",
        "hero_thumbnail": "",
        "slug": "cumhuriyet-universitesi",
        "university_id": "5576722976079872",
        "is_favourited": false,
        "is_private": false,
        "media_url": "https://storage.googleapis.com/university-images-prod/"
      },
      {
        "city": "İstanbul",
        "hero": "",
        "name": "Deniz Harp Okulu",
        "hero_thumbnail": "",
        "slug": "deniz-harp-okulu",
        "university_id": "4556376185503744",
        "is_favourited": false,
        "is_private": false,
        "media_url": "https://storage.googleapis.com/university-images-prod/"
      },
      {
        "city": "Diyarbakır",
        "hero": "",
        "name": "Dicle Üniversitesi",
        "hero_thumbnail": "",
        "slug": "dicle-universitesi",
        "university_id": "5119326138925056",
        "is_favourited": false,
        "is_private": false,
        "media_url": "https://storage.googleapis.com/university-images-prod/"
      },
      {
        "city": "Gazimağusa (KKTC)",
        "hero": "",
        "name": "Doğu Akdeniz Üniversitesi",
        "hero_thumbnail": "",
        "slug": "dogu-akdeniz-universitesi",
        "university_id": "5194092929613824",
        "is_favourited": false,
        "is_private": false,
        "media_url": "https://storage.googleapis.com/university-images-prod/"
      },
      {
        "city": "İzmir",
        "hero": "",
        "name": "Dokuz Eylül Üniversitesi",
        "hero_thumbnail": "",
        "slug": "dokuz-eylul-universitesi",
        "university_id": "5400801115635712",
        "is_favourited": false,
        "is_private": false,
        "media_url": "https://storage.googleapis.com/university-images-prod/"
      },
      {
        "city": "Kütahya",
        "hero": "",
        "name": "Dumlupınar Üniversitesi",
        "hero_thumbnail": "",
        "slug": "dumlupnar-universitesi",
        "university_id": "4697113673859072",
        "is_favourited": false,
        "is_private": false,
        "media_url": "https://storage.googleapis.com/university-images-prod/"
      },
      {
        "city": "Düzce",
        "hero": "",
        "name": "Düzce Üniversitesi",
        "hero_thumbnail": "",
        "slug": "duzce-universitesi",
        "university_id": "5260063627280384",
        "is_favourited": false,
        "is_private": false,
        "media_url": "https://storage.googleapis.com/university-images-prod/"
      },
      {
        "city": "İzmir",
        "hero": "",
        "name": "Ege Üniversitesi",
        "hero_thumbnail": "",
        "slug": "ege-universitesi",
        "university_id": "4978588650569728",
        "is_favourited": false,
        "is_private": false,
        "media_url": "https://storage.googleapis.com/university-images-prod/"
      },
      {
        "city": "Kayseri",
        "hero": "",
        "name": "Erciyes Üniversitesi",
        "hero_thumbnail": "",
        "slug": "erciyes-universitesi",
        "university_id": "5541538603991040",
        "is_favourited": false,
        "is_private": false,
        "media_url": "https://storage.googleapis.com/university-images-prod/"
      },
      {
        "city": "Erzincan",
        "hero": "",
        "name": "Erzincan Üniversitesi",
        "hero_thumbnail": "",
        "slug": "erzincan-universitesi",
        "university_id": "4626744929681408",
        "is_favourited": false,
        "is_private": false,
        "media_url": "https://storage.googleapis.com/university-images-prod/"
      },
      {
        "city": "Erzurum",
        "hero": "",
        "name": "Erzurum Teknik Üniversitesi",
        "hero_thumbnail": "",
        "slug": "erzurum-teknik-universitesi",
        "university_id": "5189694883102720",
        "is_favourited": false,
        "is_private": false,
        "media_url": "https://storage.googleapis.com/university-images-prod/"
      },
      {
        "city": "Eskişehir",
        "hero": "",
        "name": "Eskişehir Osmangazi Üniversitesi",
        "hero_thumbnail": "",
        "slug": "eskisehir-osmangazi-universitesi",
        "university_id": "4908219906392064",
        "is_favourited": false,
        "is_private": false,
        "media_url": "https://storage.googleapis.com/university-images-prod/"
      },
      {
        "city": "Elazığ",
        "hero": "",
        "name": "Fırat Üniversitesi",
        "hero_thumbnail": "",
        "slug": "frat-universitesi",
        "university_id": "5330432371458048",
        "is_favourited": false,
        "is_private": false,
        "media_url": "https://storage.googleapis.com/university-images-prod/"
      },
      {
        "city": "İstanbul",
        "hero": "",
        "name": "Galatasaray Üniversitesi",
        "hero_thumbnail": "",
        "slug": "galatasaray-universitesi",
        "university_id": "5048957394747392",
        "is_favourited": false,
        "is_private": false,
        "media_url": "https://storage.googleapis.com/university-images-prod/"
      },
      {
        "city": "Ankara",
        "hero": "",
        "name": "Gazi Üniversitesi",
        "hero_thumbnail": "",
        "slug": "gazi-universitesi",
        "university_id": "5611907348168704",
        "is_favourited": false,
        "is_private": false,
        "media_url": "https://storage.googleapis.com/university-images-prod/"
      },
      {
        "city": "Gaziantep",
        "hero": "",
        "name": "Gaziantep Üniversitesi",
        "hero_thumbnail": "",
        "slug": "gaziantep-universitesi",
        "university_id": "4512395720392704",
        "is_favourited": false,
        "is_private": false,
        "media_url": "https://storage.googleapis.com/university-images-prod/"
      },
      {
        "city": "Tokat",
        "hero": "",
        "name": "Gaziosmanpaşa Üniversitesi",
        "hero_thumbnail": "",
        "slug": "gaziosmanpasa-universitesi",
        "university_id": "5075345673814016",
        "is_favourited": false,
        "is_private": false,
        "media_url": "https://storage.googleapis.com/university-images-prod/"
      },
      {
        "city": "Kocaeli",
        "hero": "",
        "name": "Gebze Teknik Üniversitesi",
        "hero_thumbnail": "",
        "slug": "gebze-teknik-universitesi",
        "university_id": "4793870697103360",
        "is_favourited": false,
        "is_private": false,
        "media_url": "https://storage.googleapis.com/university-images-prod/"
      },
      {
        "city": "Giresun",
        "hero": "",
        "name": "Giresun Üniversitesi",
        "hero_thumbnail": "",
        "slug": "giresun-universitesi",
        "university_id": "5216083162169344",
        "is_favourited": false,
        "is_private": false,
        "media_url": "https://storage.googleapis.com/university-images-prod/"
      },
      {
        "city": "Ankara",
        "hero": "",
        "name": "Gülhane Askeri Tıp Akademisi",
        "hero_thumbnail": "",
        "slug": "gulhane-askeri-tp-akademisi",
        "university_id": "4934608185458688",
        "is_favourited": false,
        "is_private": false,
        "media_url": "https://storage.googleapis.com/university-images-prod/"
      },
      {
        "city": "Gümüşhane",
        "hero": "",
        "name": "Gümüşhane Üniversitesi",
        "hero_thumbnail": "",
        "slug": "gumushane-universitesi",
        "university_id": "5497558138880000",
        "is_favourited": false,
        "is_private": false,
        "media_url": "https://storage.googleapis.com/university-images-prod/"
      },
      {
        "city": "Ankara",
        "hero": "",
        "name": "Hacettepe Üniversitesi",
        "hero_thumbnail": "",
        "slug": "hacettepe-universitesi",
        "university_id": "4582764464570368",
        "is_favourited": false,
        "is_private": false,
        "media_url": "https://storage.googleapis.com/university-images-prod/"
      },
      {
        "city": "Hakkari",
        "hero": "",
        "name": "Hakkari Üniversitesi",
        "hero_thumbnail": "",
        "slug": "hakkari-universitesi",
        "university_id": "5145714417991680",
        "is_favourited": false,
        "is_private": false,
        "media_url": "https://storage.googleapis.com/university-images-prod/"
      },
      {
        "city": "Şanlıurfa",
        "hero": "",
        "name": "Harran Üniversitesi",
        "hero_thumbnail": "",
        "slug": "harran-universitesi",
        "university_id": "5427189394702336",
        "is_favourited": false,
        "is_private": false,
        "media_url": "https://storage.googleapis.com/university-images-prod/"
      },
      {
        "city": "İstanbul",
        "hero": "",
        "name": "Hava Harp Okulu",
        "hero_thumbnail": "",
        "slug": "hava-harp-okulu",
        "university_id": "5286451906347008",
        "is_favourited": false,
        "is_private": false,
        "media_url": "https://storage.googleapis.com/university-images-prod/"
      },
      {
        "city": "Çorum",
        "hero": "",
        "name": "Hitit Üniversitesi",
        "hero_thumbnail": "",
        "slug": "hitit-universitesi",
        "university_id": "5004976929636352",
        "is_favourited": false,
        "is_private": false,
        "media_url": "https://storage.googleapis.com/university-images-prod/"
      },
      {
        "city": "Türkistan (Kazakistan)",
        "hero": "",
        "name": "Hoca Ahmet Yesevi Uluslararası Türk-kazak Üniversitesi",
        "hero_thumbnail": "",
        "slug": "hoca-ahmet-yesevi-uluslararas-turk-kazak-universitesi",
        "university_id": "4982986697080832",
        "is_favourited": false,
        "is_private": false,
        "media_url": "https://storage.googleapis.com/university-images-prod/"
      },
      {
        "city": "Iğdır",
        "hero": "",
        "name": "Iğdır Üniversitesi",
        "hero_thumbnail": "",
        "slug": "igdr-universitesi",
        "university_id": "5567926883057664",
        "is_favourited": false,
        "is_private": false,
        "media_url": "https://storage.googleapis.com/university-images-prod/"
      },
      {
        "city": "Malatya",
        "hero": "",
        "name": "İnönü Üniversitesi",
        "hero_thumbnail": "",
        "slug": "inonu-universitesi",
        "university_id": "5110530045902848",
        "is_favourited": false,
        "is_private": false,
        "media_url": "https://storage.googleapis.com/university-images-prod/"
      },
      {
        "city": "Hatay",
        "hero": "",
        "name": "İskenderun Teknik Üniversitesi",
        "hero_thumbnail": "",
        "slug": "iskenderun-teknik-universitesi",
        "university_id": "4688317580836864",
        "is_favourited": false,
        "is_private": false,
        "media_url": "https://storage.googleapis.com/university-images-prod/"
      },
      {
        "city": "İstanbul",
        "hero": "",
        "name": "İstanbul Medeniyet Üniversitesi",
        "hero_thumbnail": "",
        "slug": "istanbul-medeniyet-universitesi",
        "university_id": "5040161301725184",
        "is_favourited": false,
        "is_private": false,
        "media_url": "https://storage.googleapis.com/university-images-prod/"
      },
      {
        "city": "İstanbul",
        "hero": "",
        "name": "İstanbul Teknik Üniversitesi",
        "hero_thumbnail": "",
        "slug": "istanbul-teknik-universitesi",
        "university_id": "4811462883147776",
        "is_favourited": false,
        "is_private": false,
        "media_url": "https://storage.googleapis.com/university-images-prod/"
      },
      {
        "city": "İstanbul",
        "hero": "",
        "name": "İstanbul Üniversitesi",
        "hero_thumbnail": "",
        "slug": "istanbul-universitesi",
        "university_id": "4670725394792448",
        "is_favourited": false,
        "is_private": false,
        "media_url": "https://storage.googleapis.com/university-images-prod/"
      },
      {
        "city": "Tİflis (Gürcistan)",
        "hero": "",
        "name": "İvane Javakhishvili Tiflis Devlet Üniversitesi",
        "hero_thumbnail": "",
        "slug": "ivane-javakhishvili-tiflis-devlet-universitesi",
        "university_id": "5572324929568768",
        "is_favourited": false,
        "is_private": false,
        "media_url": "https://storage.googleapis.com/university-images-prod/"
      },
      {
        "city": "İzmir",
        "hero": "",
        "name": "İzmir Katip Çelebi Üniversitesi",
        "hero_thumbnail": "",
        "slug": "izmir-katip-celebi-universitesi",
        "university_id": "4952200371503104",
        "is_favourited": false,
        "is_private": false,
        "media_url": "https://storage.googleapis.com/university-images-prod/"
      },
      {
        "city": "İzmir",
        "hero": "",
        "name": "İzmir Yüksek Teknoloji Enstitüsü",
        "hero_thumbnail": "",
        "slug": "izmir-yuksek-teknoloji-enstitusu",
        "university_id": "4600356650614784",
        "is_favourited": false,
        "is_private": false,
        "media_url": "https://storage.googleapis.com/university-images-prod/"
      },
      {
        "city": "Kars",
        "hero": "",
        "name": "Kafkas Üniversitesi",
        "hero_thumbnail": "",
        "slug": "kafkas-universitesi",
        "university_id": "4881831627325440",
        "is_favourited": false,
        "is_private": false,
        "media_url": "https://storage.googleapis.com/university-images-prod/"
      },
      {
        "city": "Kars",
        "hero": "",
        "name": "Kahramanmaraş Sütçü İmam Üniversitesi",
        "hero_thumbnail": "",
        "slug": "kahramanmaras-sutcu-imam-universitesi",
        "university_id": "5444781580746752",
        "is_favourited": false,
        "is_private": false,
        "media_url": "https://storage.googleapis.com/university-images-prod/"
      },
      {
        "city": "Ankara",
        "hero": "",
        "name": "Kara Harp Okulu",
        "hero_thumbnail": "",
        "slug": "kara-harp-okulu",
        "university_id": "5304044092391424",
        "is_favourited": false,
        "is_private": false,
        "media_url": "https://storage.googleapis.com/university-images-prod/"
      },
      {
        "city": "Karabük",
        "hero": "",
        "name": "Karabük Üniversitesi",
        "hero_thumbnail": "",
        "slug": "karabuk-universitesi",
        "university_id": "5022569115680768",
        "is_favourited": false,
        "is_private": false,
        "media_url": "https://storage.googleapis.com/university-images-prod/"
      },
      {
        "city": "Trabzon",
        "hero": "",
        "name": "Karadeniz Teknik Üniversitesi",
        "hero_thumbnail": "",
        "slug": "karadeniz-teknik-universitesi",
        "university_id": "5585519069102080",
        "is_favourited": false,
        "is_private": false,
        "media_url": "https://storage.googleapis.com/university-images-prod/"
      },
      {
        "city": "Karaman",
        "hero": "",
        "name": "Karamanoğlu Mehmetbey Üniversitesi",
        "hero_thumbnail": "",
        "slug": "karamanoglu-mehmetbey-universitesi",
        "university_id": "4565172278525952",
        "is_favourited": false,
        "is_private": false,
        "media_url": "https://storage.googleapis.com/university-images-prod/"
      },
      {
        "city": "Kastamonu",
        "hero": "",
        "name": "Kastamonu Üniversitesi",
        "hero_thumbnail": "",
        "slug": "kastamonu-universitesi",
        "university_id": "5128122231947264",
        "is_favourited": false,
        "is_private": false,
        "media_url": "https://storage.googleapis.com/university-images-prod/"
      },
      {
        "city": "Kilis",
        "hero": "",
        "name": "Kilis 7 Aralık Üniversitesi",
        "hero_thumbnail": "",
        "slug": "kilis-7-aralk-universitesi",
        "university_id": "4846647255236608",
        "is_favourited": false,
        "is_private": false,
        "media_url": "https://storage.googleapis.com/university-images-prod/"
      },
      {
        "city": "Kocaeli",
        "hero": "",
        "name": "Kocaeli Üniversitesi",
        "hero_thumbnail": "",
        "slug": "kocaeli-universitesi",
        "university_id": "4987384743591936",
        "is_favourited": false,
        "is_private": false,
        "media_url": "https://storage.googleapis.com/university-images-prod/"
      },
      {
        "city": "Komrat (Moldova)",
        "hero": "",
        "name": "Komrat Devlet Üniversitesi",
        "hero_thumbnail": "",
        "slug": "komrat-devlet-universitesi",
        "university_id": "4833453115703296",
        "is_favourited": false,
        "is_private": false,
        "media_url": "https://storage.googleapis.com/university-images-prod/"
      },
      {
        "city": "Bişkek (Kırgızistan)",
        "hero": "",
        "name": "Kırgızistan-türkiye Manas Üniversitesi",
        "hero_thumbnail": "",
        "slug": "krgzistan-turkiye-manas-universitesi",
        "university_id": "5545936650502144",
        "is_favourited": false,
        "is_private": false,
        "media_url": "https://storage.googleapis.com/university-images-prod/"
      },
      {
        "city": "Kırıkkale",
        "hero": "",
        "name": "Kırıkkale Üniversitesi",
        "hero_thumbnail": "",
        "slug": "krkkale-universitesi",
        "university_id": "5409597208657920",
        "is_favourited": false,
        "is_private": false,
        "media_url": "https://storage.googleapis.com/university-images-prod/"
      },
      {
        "city": "Kırklareli",
        "hero": "",
        "name": "Kırklareli Üniversitesi",
        "hero_thumbnail": "",
        "slug": "krklareli-universitesi",
        "university_id": "4705909766881280",
        "is_favourited": false,
        "is_private": false,
        "media_url": "https://storage.googleapis.com/university-images-prod/"
      },
      {
        "city": "Mardin",
        "hero": "",
        "name": "Mardin Artuklu Üniversitesi",
        "hero_thumbnail": "",
        "slug": "mardin-artuklu-universitesi",
        "university_id": "4917015999414272",
        "is_favourited": false,
        "is_private": false,
        "media_url": "https://storage.googleapis.com/university-images-prod/"
      },
      {
        "city": "İstanbul",
        "hero": "",
        "name": "Marmara Üniversitesi",
        "hero_thumbnail": "",
        "slug": "marmara-universitesi",
        "university_id": "5479965952835584",
        "is_favourited": false,
        "is_private": false,
        "media_url": "https://storage.googleapis.com/university-images-prod/"
      },
      {
        "city": "Burdur",
        "hero": "",
        "name": "Mehmet Akif Ersoy Üniversitesi",
        "hero_thumbnail": "",
        "slug": "mehmet-akif-ersoy-universitesi",
        "university_id": "5339228464480256",
        "is_favourited": false,
        "is_private": false,
        "media_url": "https://storage.googleapis.com/university-images-prod/"
      },
      {
        "city": "Mersin",
        "hero": "",
        "name": "Mersin Üniversitesi",
        "hero_thumbnail": "",
        "slug": "mersin-universitesi",
        "university_id": "5620703441190912",
        "is_favourited": false,
        "is_private": false,
        "media_url": "https://storage.googleapis.com/university-images-prod/"
      },
      {
        "city": "İstanbul",
        "hero": "",
        "name": "Mimar Sinan Güzel Sanatlar Üniversitesi",
        "hero_thumbnail": "",
        "slug": "mimar-sinan-guzel-sanatlar-universitesi",
        "university_id": "5070947627302912",
        "is_favourited": false,
        "is_private": false,
        "media_url": "https://storage.googleapis.com/university-images-prod/"
      },
      {
        "city": "Muğla",
        "hero": "",
        "name": "Muğla Sıtkı Koçman Üniversitesi",
        "hero_thumbnail": "",
        "slug": "mugla-stk-kocman-universitesi",
        "university_id": "4789472650592256",
        "is_favourited": false,
        "is_private": false,
        "media_url": "https://storage.googleapis.com/university-images-prod/"
      },
      {
        "city": "Muş",
        "hero": "",
        "name": "Muş Alparslan Üniversitesi",
        "hero_thumbnail": "",
        "slug": "mus-alparslan-universitesi",
        "university_id": "4648735162236928",
        "is_favourited": false,
        "is_private": false,
        "media_url": "https://storage.googleapis.com/university-images-prod/"
      },
      {
        "city": "Hatay",
        "hero": "",
        "name": "Mustafa Kemal Üniversitesi",
        "hero_thumbnail": "",
        "slug": "mustafa-kemal-universitesi",
        "university_id": "5211685115658240",
        "is_favourited": false,
        "is_private": false,
        "media_url": "https://storage.googleapis.com/university-images-prod/"
      },
      {
        "city": "Nahcivan (Azerbaycan)",
        "hero": "",
        "name": "Nahcivan Devlet Üniversitesi",
        "hero_thumbnail": "",
        "slug": "nahcivan-devlet-universitesi",
        "university_id": "4868637487792128",
        "is_favourited": false,
        "is_private": false,
        "media_url": "https://storage.googleapis.com/university-images-prod/"
      },
      {
        "city": "Tekirdağ",
        "hero": "",
        "name": "Namık Kemal Üniversitesi",
        "hero_thumbnail": "",
        "slug": "namk-kemal-universitesi",
        "university_id": "4930210138947584",
        "is_favourited": false,
        "is_private": false,
        "media_url": "https://storage.googleapis.com/university-images-prod/"
      },
      {
        "city": "Konya",
        "hero": "",
        "name": "Necmettin Erbakan Üniversitesi",
        "hero_thumbnail": "",
        "slug": "necmettin-erbakan-universitesi",
        "university_id": "5493160092368896",
        "is_favourited": false,
        "is_private": false,
        "media_url": "https://storage.googleapis.com/university-images-prod/"
      },
      {
        "city": "Nevşehir",
        "hero": "",
        "name": "Nevşehir Hacı Bektaş Veli Üniversitesi",
        "hero_thumbnail": "",
        "slug": "nevsehir-hac-bektas-veli-universitesi",
        "university_id": "4578366418059264",
        "is_favourited": false,
        "is_private": false,
        "media_url": "https://storage.googleapis.com/university-images-prod/"
      },
      {
        "city": "Niğde",
        "hero": "",
        "name": "Niğde Üniversitesi",
        "hero_thumbnail": "",
        "slug": "nigde-universitesi",
        "university_id": "5141316371480576",
        "is_favourited": false,
        "is_private": false,
        "media_url": "https://storage.googleapis.com/university-images-prod/"
      },
      {
        "city": "Samsun",
        "hero": "",
        "name": "Ondokuz Mayıs Üniversitesi",
        "hero_thumbnail": "",
        "slug": "ondokuz-mays-universitesi",
        "university_id": "5282053859835904",
        "is_favourited": false,
        "is_private": false,
        "media_url": "https://storage.googleapis.com/university-images-prod/"
      },
      {
        "city": "Ordu",
        "hero": "",
        "name": "Ordu Üniversitesi",
        "hero_thumbnail": "",
        "slug": "ordu-universitesi",
        "university_id": "5000578883125248",
        "is_favourited": false,
        "is_private": false,
        "media_url": "https://storage.googleapis.com/university-images-prod/"
      },
      {
        "city": "Ankara",
        "hero": "",
        "name": "Orta Doğu Teknik Üniversitesi",
        "hero_thumbnail": "",
        "slug": "orta-dogu-teknik-universitesi",
        "university_id": "5563528836546560",
        "is_favourited": false,
        "is_private": false,
        "media_url": "https://storage.googleapis.com/university-images-prod/"
      },
      {
        "city": "Osmaniye",
        "hero": "",
        "name": "Osmaniye Korkut Ata Üniversitesi",
        "hero_thumbnail": "",
        "slug": "osmaniye-korkut-ata-universitesi",
        "university_id": "4543182045970432",
        "is_favourited": false,
        "is_private": false,
        "media_url": "https://storage.googleapis.com/university-images-prod/"
      },
      {
        "city": "Denizli",
        "hero": "",
        "name": "Pamukkale Üniversitesi",
        "hero_thumbnail": "",
        "slug": "pamukkale-universitesi",
        "university_id": "4824657022681088",
        "is_favourited": false,
        "is_private": false,
        "media_url": "https://storage.googleapis.com/university-images-prod/"
      },
      {
        "city": "Rize",
        "hero": "",
        "name": "Recep Tayyip Erdoğan Üniversitesi",
        "hero_thumbnail": "",
        "slug": "recep-tayyip-erdogan-universitesi",
        "university_id": "4683919534325760",
        "is_favourited": false,
        "is_private": false,
        "media_url": "https://storage.googleapis.com/university-images-prod/"
      },
      {
        "city": "Sakarya",
        "hero": "",
        "name": "Sakarya Üniversitesi",
        "hero_thumbnail": "",
        "slug": "sakarya-universitesi",
        "university_id": "4965394511036416",
        "is_favourited": false,
        "is_private": false,
        "media_url": "https://storage.googleapis.com/university-images-prod/"
      },
      {
        "city": "Konya",
        "hero": "",
        "name": "Selçuk Üniversitesi",
        "hero_thumbnail": "",
        "slug": "selcuk-universitesi",
        "university_id": "5176500743569408",
        "is_favourited": false,
        "is_private": false,
        "media_url": "https://storage.googleapis.com/university-images-prod/"
      },
      {
        "city": "Siirt",
        "hero": "",
        "name": "Siirt Üniversitesi",
        "hero_thumbnail": "",
        "slug": "siirt-universitesi",
        "university_id": "5457975720280064",
        "is_favourited": false,
        "is_private": false,
        "media_url": "https://storage.googleapis.com/university-images-prod/"
      },
      {
        "city": "Sinop",
        "hero": "",
        "name": "Sinop Üniversitesi",
        "hero_thumbnail": "",
        "slug": "sinop-universitesi",
        "university_id": "4754288278503424",
        "is_favourited": false,
        "is_private": false,
        "media_url": "https://storage.googleapis.com/university-images-prod/"
      },
      {
        "city": "Batum (Gürcistan)",
        "hero": "",
        "name": "Şota Rustaveli Devlet Üniversitesi",
        "hero_thumbnail": "",
        "slug": "sota-rustaveli-devlet-universitesi",
        "university_id": "4551978138992640",
        "is_favourited": false,
        "is_private": false,
        "media_url": "https://storage.googleapis.com/university-images-prod/"
      },
      {
        "city": "Şırnak",
        "hero": "",
        "name": "Şırnak Üniversitesi",
        "hero_thumbnail": "",
        "slug": "srnak-universitesi",
        "university_id": "5317238231924736",
        "is_favourited": false,
        "is_private": false,
        "media_url": "https://storage.googleapis.com/university-images-prod/"
      },
      {
        "city": "Isparta",
        "hero": "",
        "name": "Süleyman Demirel Üniversitesi",
        "hero_thumbnail": "",
        "slug": "suleyman-demirel-universitesi",
        "university_id": "5035763255214080",
        "is_favourited": false,
        "is_private": false,
        "media_url": "https://storage.googleapis.com/university-images-prod/"
      },
      {
        "city": "Sumgayıt (Azerbaycan)",
        "hero": "",
        "name": "Sumgayıt Devlet Üniversitesi",
        "hero_thumbnail": "",
        "slug": "sumgayt-devlet-universitesi",
        "university_id": "4727899999436800",
        "is_favourited": false,
        "is_private": false,
        "media_url": "https://storage.googleapis.com/university-images-prod/"
      },
      {
        "city": "Edirne",
        "hero": "",
        "name": "Trakya Üniversitesi",
        "hero_thumbnail": "",
        "slug": "trakya-universitesi",
        "university_id": "5370014790057984",
        "is_favourited": false,
        "is_private": false,
        "media_url": "https://storage.googleapis.com/university-images-prod/"
      },
      {
        "city": "Tunceli",
        "hero": "",
        "name": "Tunceli Üniversitesi",
        "hero_thumbnail": "",
        "slug": "tunceli-universitesi",
        "university_id": "4666327348281344",
        "is_favourited": false,
        "is_private": false,
        "media_url": "https://storage.googleapis.com/university-images-prod/"
      },
      {
        "city": "İstanbul",
        "hero": "",
        "name": "Türk-alman Üniversitesi",
        "hero_thumbnail": "",
        "slug": "turk-alman-universitesi",
        "university_id": "5510752278413312",
        "is_favourited": false,
        "is_private": false,
        "media_url": "https://storage.googleapis.com/university-images-prod/"
      },
      {
        "city": "Bursa",
        "hero": "",
        "name": "Uludağ Üniversitesi",
        "hero_thumbnail": "",
        "slug": "uludag-universitesi",
        "university_id": "5158908557524992",
        "is_favourited": false,
        "is_private": false,
        "media_url": "https://storage.googleapis.com/university-images-prod/"
      },
      {
        "city": "Uşak",
        "hero": "",
        "name": "Uşak Üniversitesi",
        "hero_thumbnail": "",
        "slug": "usak-universitesi",
        "university_id": "5440383534235648",
        "is_favourited": false,
        "is_private": false,
        "media_url": "https://storage.googleapis.com/university-images-prod/"
      },
      {
        "city": "Yalova",
        "hero": "",
        "name": "Yalova Üniversitesi",
        "hero_thumbnail": "",
        "slug": "yalova-universitesi",
        "university_id": "5299646045880320",
        "is_favourited": false,
        "is_private": false,
        "media_url": "https://storage.googleapis.com/university-images-prod/"
      },
      {
        "city": "Ankara",
        "hero": "",
        "name": "Yıldırım Beyazıt Üniversitesi",
        "hero_thumbnail": "",
        "slug": "yldrm-beyazt-universitesi",
        "university_id": "5123724185436160",
        "is_favourited": false,
        "is_private": false,
        "media_url": "https://storage.googleapis.com/university-images-prod/"
      },
      {
        "city": "İstanbul",
        "hero": "",
        "name": "Yıldız Teknik Üniversitesi",
        "hero_thumbnail": "",
        "slug": "yldz-teknik-universitesi",
        "university_id": "4842249208725504",
        "is_favourited": false,
        "is_private": false,
        "media_url": "https://storage.googleapis.com/university-images-prod/"
      },
      {
        "city": "Van",
        "hero": "",
        "name": "Yüzüncü Yıl Üniversitesi",
        "hero_thumbnail": "",
        "slug": "yuzuncu-yl-universitesi",
        "university_id": "4701511720370176",
        "is_favourited": false,
        "is_private": false,
        "media_url": "https://storage.googleapis.com/university-images-prod/"
      }
    ]
  },
  "private": {
    "count": 71,
    "results": [
      {
        "city": "İstanbul",
        "hero": "",
        "name": "Acıbadem Üniversitesi",
        "hero_thumbnail": "",
        "slug": "acbadem-universitesi",
        "university_id": "5348024557502464",
        "is_favourited": false,
        "is_private": true,
        "media_url": "https://storage.googleapis.com/university-images-prod/"
      },
      {
        "city": "Lefkoşa (KKTC)",
        "hero": "",
        "name": "Akdeniz Karpaz Üniversitesi",
        "hero_thumbnail": "",
        "slug": "akdeniz-karpaz-universitesi",
        "university_id": "4631142976192512",
        "is_favourited": false,
        "is_private": true,
        "media_url": "https://storage.googleapis.com/university-images-prod/"
      },
      {
        "city": "Antalya",
        "hero": "",
        "name": "Alanya Hamdullah Emin Paşa Üniversitesi",
        "hero_thumbnail": "",
        "slug": "alanya-hamdullah-emin-pasa-universitesi",
        "university_id": "5277655813324800",
        "is_favourited": false,
        "is_private": true,
        "media_url": "https://storage.googleapis.com/university-images-prod/"
      },
      {
        "city": "İstanbul",
        "hero": "",
        "name": "Atılım Üniversitesi",
        "hero_thumbnail": "",
        "slug": "atlm-universitesi",
        "university_id": "4679521487814656",
        "is_favourited": false,
        "is_private": true,
        "media_url": "https://storage.googleapis.com/university-images-prod/"
      },
      {
        "city": "Trabzon",
        "hero": "",
        "name": "Avrasya Üniversitesi",
        "hero_thumbnail": "",
        "slug": "avrasya-universitesi",
        "university_id": "5242471441235968",
        "is_favourited": false,
        "is_private": true,
        "media_url": "https://storage.googleapis.com/university-images-prod/"
      },
      {
        "city": "İstanbul",
        "hero": "",
        "name": "Bahçeşehir Üniversitesi",
        "hero_thumbnail": "",
        "slug": "bahcesehir-universitesi",
        "university_id": "4960996464525312",
        "is_favourited": false,
        "is_private": true,
        "media_url": "https://storage.googleapis.com/university-images-prod/"
      },
      {
        "city": "Ankara",
        "hero": "",
        "name": "Başkent Üniversitesi",
        "hero_thumbnail": "",
        "slug": "baskent-universitesi",
        "university_id": "4890627720347648",
        "is_favourited": false,
        "is_private": true,
        "media_url": "https://storage.googleapis.com/university-images-prod/"
      },
      {
        "city": "İstanbul",
        "hero": "",
        "name": "Beykent Üniversitesi",
        "hero_thumbnail": "",
        "slug": "beykent-universitesi",
        "university_id": "5312840185413632",
        "is_favourited": false,
        "is_private": true,
        "media_url": "https://storage.googleapis.com/university-images-prod/"
      },
      {
        "city": "İstanbul",
        "hero": "",
        "name": "Bezm-i Âlem Vakıf Üniversitesi",
        "hero_thumbnail": "",
        "slug": "bezm-i-alem-vakf-universitesi",
        "university_id": "5031365208702976",
        "is_favourited": false,
        "is_private": true,
        "media_url": "https://storage.googleapis.com/university-images-prod/"
      },
      {
        "city": "İstanbul",
        "hero": "",
        "name": "Biruni Üniversitesi",
        "hero_thumbnail": "",
        "slug": "biruni-universitesi",
        "university_id": "5084141766836224",
        "is_favourited": false,
        "is_private": true,
        "media_url": "https://storage.googleapis.com/university-images-prod/"
      },
      {
        "city": "Mersin",
        "hero": "",
        "name": "Çağ Üniversitesi",
        "hero_thumbnail": "",
        "slug": "cag-universitesi",
        "university_id": "4591560557592576",
        "is_favourited": false,
        "is_private": true,
        "media_url": "https://storage.googleapis.com/university-images-prod/"
      },
      {
        "city": "Ankara",
        "hero": "",
        "name": "Çankaya Üniversitesi",
        "hero_thumbnail": "",
        "slug": "cankaya-universitesi",
        "university_id": "5435985487724544",
        "is_favourited": false,
        "is_private": true,
        "media_url": "https://storage.googleapis.com/university-images-prod/"
      },
      {
        "city": "İstanbul",
        "hero": "",
        "name": "Doğuş Üniversitesi",
        "hero_thumbnail": "",
        "slug": "dogus-universitesi",
        "university_id": "4837851162214400",
        "is_favourited": false,
        "is_private": true,
        "media_url": "https://storage.googleapis.com/university-images-prod/"
      },
      {
        "city": "İstanbul",
        "hero": "",
        "name": "Fatih Sultan Mehmet Vakıf Üniversitesi",
        "hero_thumbnail": "",
        "slug": "fatih-sultan-mehmet-vakf-universitesi",
        "university_id": "5471169859813376",
        "is_favourited": false,
        "is_private": true,
        "media_url": "https://storage.googleapis.com/university-images-prod/"
      },
      {
        "city": "İstanbul",
        "hero": "",
        "name": "Gedik Üniversitesi",
        "hero_thumbnail": "",
        "slug": "gedik-universitesi",
        "university_id": "5356820650524672",
        "is_favourited": false,
        "is_private": true,
        "media_url": "https://storage.googleapis.com/university-images-prod/"
      },
      {
        "city": "Girne (KKTC)",
        "hero": "",
        "name": "Girne Amerikan Üniversitesi",
        "hero_thumbnail": "",
        "slug": "girne-amerikan-universitesi",
        "university_id": "4912617952903168",
        "is_favourited": false,
        "is_private": true,
        "media_url": "https://storage.googleapis.com/university-images-prod/"
      },
      {
        "city": "Girne (KKTC)",
        "hero": "",
        "name": "Girne Üniversitesi",
        "hero_thumbnail": "",
        "slug": "girne-universitesi",
        "university_id": "5475567906324480",
        "is_favourited": false,
        "is_private": true,
        "media_url": "https://storage.googleapis.com/university-images-prod/"
      },
      {
        "city": "İstanbul",
        "hero": "",
        "name": "Haliç Üniversitesi",
        "hero_thumbnail": "",
        "slug": "halic-universitesi",
        "university_id": "4864239441281024",
        "is_favourited": false,
        "is_private": true,
        "media_url": "https://storage.googleapis.com/university-images-prod/"
      },
      {
        "city": "Gaziantep",
        "hero": "",
        "name": "Hasan Kalyoncu Üniversitesi",
        "hero_thumbnail": "",
        "slug": "hasan-kalyoncu-universitesi",
        "university_id": "4723501952925696",
        "is_favourited": false,
        "is_private": true,
        "media_url": "https://storage.googleapis.com/university-images-prod/"
      },
      {
        "city": "Ankara",
        "hero": "",
        "name": "İhsan Doğramacı Bilkent Üniversitesi",
        "hero_thumbnail": "",
        "slug": "ihsan-dogramac-bilkent-universitesi",
        "university_id": "4547580092481536",
        "is_favourited": false,
        "is_private": true,
        "media_url": "https://storage.googleapis.com/university-images-prod/"
      },
      {
        "city": "İstanbul",
        "hero": "",
        "name": "Işık Üniversitesi",
        "hero_thumbnail": "",
        "slug": "isk-universitesi",
        "university_id": "5392005022613504",
        "is_favourited": false,
        "is_private": true,
        "media_url": "https://storage.googleapis.com/university-images-prod/"
      },
      {
        "city": "İstanbul",
        "hero": "",
        "name": "İstanbul 29 Mayıs Üniversitesi",
        "hero_thumbnail": "",
        "slug": "istanbul-29-mays-universitesi",
        "university_id": "5251267534258176",
        "is_favourited": false,
        "is_private": true,
        "media_url": "https://storage.googleapis.com/university-images-prod/"
      },
      {
        "city": "İstanbul",
        "hero": "",
        "name": "İstanbul Arel Üniversitesi",
        "hero_thumbnail": "",
        "slug": "istanbul-arel-universitesi",
        "university_id": "4969792557547520",
        "is_favourited": false,
        "is_private": true,
        "media_url": "https://storage.googleapis.com/university-images-prod/"
      },
      {
        "city": "İstanbul",
        "hero": "",
        "name": "İstanbul Aydın Üniversitesi",
        "hero_thumbnail": "",
        "slug": "istanbul-aydn-universitesi",
        "university_id": "5532742510968832",
        "is_favourited": false,
        "is_private": true,
        "media_url": "https://storage.googleapis.com/university-images-prod/"
      },
      {
        "city": "İstanbul",
        "hero": "",
        "name": "İstanbul Bilgi Üniversitesi",
        "hero_thumbnail": "",
        "slug": "istanbul-bilgi-universitesi",
        "university_id": "4617948836659200",
        "is_favourited": false,
        "is_private": true,
        "media_url": "https://storage.googleapis.com/university-images-prod/"
      },
      {
        "city": "İstanbul",
        "hero": "",
        "name": "İstanbul Bilim Üniversitesi",
        "hero_thumbnail": "",
        "slug": "istanbul-bilim-universitesi",
        "university_id": "5180898790080512",
        "is_favourited": false,
        "is_private": true,
        "media_url": "https://storage.googleapis.com/university-images-prod/"
      },
      {
        "city": "İstanbul",
        "hero": "",
        "name": "İstanbul Esenyurt Üniversitesi",
        "hero_thumbnail": "",
        "slug": "istanbul-esenyurt-universitesi",
        "university_id": "4899423813369856",
        "is_favourited": false,
        "is_private": true,
        "media_url": "https://storage.googleapis.com/university-images-prod/"
      },
      {
        "city": "İstanbul",
        "hero": "",
        "name": "İstanbul Gelişim Üniversitesi",
        "hero_thumbnail": "",
        "slug": "istanbul-gelisim-universitesi",
        "university_id": "5462373766791168",
        "is_favourited": false,
        "is_private": true,
        "media_url": "https://storage.googleapis.com/university-images-prod/"
      },
      {
        "city": "İstanbul",
        "hero": "",
        "name": "İstanbul Kemerburgaz Üniversitesi",
        "hero_thumbnail": "",
        "slug": "istanbul-kemerburgaz-universitesi",
        "university_id": "4758686325014528",
        "is_favourited": false,
        "is_private": true,
        "media_url": "https://storage.googleapis.com/university-images-prod/"
      },
      {
        "city": "İstanbul",
        "hero": "",
        "name": "İstanbul Kültür Üniversitesi",
        "hero_thumbnail": "",
        "slug": "istanbul-kultur-universitesi",
        "university_id": "5321636278435840",
        "is_favourited": false,
        "is_private": true,
        "media_url": "https://storage.googleapis.com/university-images-prod/"
      },
      {
        "city": "İstanbul",
        "hero": "",
        "name": "İstanbul Medipol Üniversitesi",
        "hero_thumbnail": "",
        "slug": "istanbul-medipol-universitesi",
        "university_id": "5603111255146496",
        "is_favourited": false,
        "is_private": true,
        "media_url": "https://storage.googleapis.com/university-images-prod/"
      },
      {
        "city": "İstanbul",
        "hero": "istanbul-rumeli-universitesi/hero.jpg",
        "name": "İstanbul Rumeli Üniversitesi",
        "hero_thumbnail": "",
        "slug": "istanbul-rumeli-universitesi",
        "university_id": "4690166698475520",
        "is_favourited": false,
        "is_private": true,
        "media_url": "https://storage.googleapis.com/university-images-prod/"
      },
      {
        "city": "İstanbul",
        "hero": "",
        "name": "İstanbul Sabahattin Zaim Üniversitesi",
        "hero_thumbnail": "",
        "slug": "istanbul-sabahattin-zaim-universitesi",
        "university_id": "4529987906437120",
        "is_favourited": false,
        "is_private": true,
        "media_url": "https://storage.googleapis.com/university-images-prod/"
      },
      {
        "city": "İstanbul",
        "hero": "",
        "name": "İstanbul Şehir Üniversitesi",
        "hero_thumbnail": "",
        "slug": "istanbul-sehir-universitesi",
        "university_id": "5092937859858432",
        "is_favourited": false,
        "is_private": true,
        "media_url": "https://storage.googleapis.com/university-images-prod/"
      },
      {
        "city": "İstanbul",
        "hero": "",
        "name": "İstanbul Ticaret Üniversitesi",
        "hero_thumbnail": "",
        "slug": "istanbul-ticaret-universitesi",
        "university_id": "5374412836569088",
        "is_favourited": false,
        "is_private": true,
        "media_url": "https://storage.googleapis.com/university-images-prod/"
      },
      {
        "city": "İstanbul",
        "hero": "istinye-universitesi/hero.jpg",
        "name": "İstinye Üniversitesi",
        "hero_thumbnail": "",
        "slug": "istinye-universitesi",
        "university_id": "5393854140252160",
        "is_favourited": false,
        "is_private": true,
        "media_url": "https://storage.googleapis.com/university-images-prod/"
      },
      {
        "city": "İzmir",
        "hero": "",
        "name": "İzmir Ekonomi Üniversitesi",
        "hero_thumbnail": "",
        "slug": "izmir-ekonomi-universitesi",
        "university_id": "5233675348213760",
        "is_favourited": false,
        "is_private": true,
        "media_url": "https://storage.googleapis.com/university-images-prod/"
      },
      {
        "city": "İstanbul",
        "hero": "",
        "name": "Kadir Has Üniversitesi",
        "hero_thumbnail": "",
        "slug": "kadir-has-universitesi",
        "university_id": "5163306604036096",
        "is_favourited": false,
        "is_private": true,
        "media_url": "https://storage.googleapis.com/university-images-prod/"
      },
      {
        "city": "Lefkoşa (KKTC)",
        "hero": "",
        "name": "Kıbrıs Amerikan Üniversitesi",
        "hero_thumbnail": "",
        "slug": "kbrs-amerikan-universitesi",
        "university_id": "4771880464547840",
        "is_favourited": false,
        "is_private": true,
        "media_url": "https://storage.googleapis.com/university-images-prod/"
      },
      {
        "city": "Lefkoşa (KKTC)",
        "hero": "",
        "name": "Kıbrıs Sosyal Bilimler Üniversitesi",
        "hero_thumbnail": "",
        "slug": "kbrs-sosyal-bilimler-universitesi",
        "university_id": "5334830417969152",
        "is_favourited": false,
        "is_private": true,
        "media_url": "https://storage.googleapis.com/university-images-prod/"
      },
      {
        "city": "İstanbul",
        "hero": "",
        "name": "Koç Üniversitesi",
        "hero_thumbnail": "",
        "slug": "koc-universitesi",
        "university_id": "5268859720302592",
        "is_favourited": false,
        "is_private": true,
        "media_url": "https://storage.googleapis.com/university-images-prod/"
      },
      {
        "city": "Konya",
        "hero": "",
        "name": "Konya Gıda Ve Tarım Üniversitesi",
        "hero_thumbnail": "",
        "slug": "konya-gda-ve-tarm-universitesi",
        "university_id": "5550334697013248",
        "is_favourited": false,
        "is_private": true,
        "media_url": "https://storage.googleapis.com/university-images-prod/"
      },
      {
        "city": "Konya",
        "hero": "",
        "name": "Kto Karatay Üniversitesi",
        "hero_thumbnail": "",
        "slug": "kto-karatay-universitesi",
        "university_id": "4635541022703616",
        "is_favourited": false,
        "is_private": true,
        "media_url": "https://storage.googleapis.com/university-images-prod/"
      },
      {
        "city": "Lefke (KKTC)",
        "hero": "",
        "name": "Lefke Avrupa Üniversitesi",
        "hero_thumbnail": "",
        "slug": "lefke-avrupa-universitesi",
        "university_id": "5053355441258496",
        "is_favourited": false,
        "is_private": true,
        "media_url": "https://storage.googleapis.com/university-images-prod/"
      },
      {
        "city": "Lefkoşa (KKTC)",
        "hero": "",
        "name": "Lefkoşa İngiliz Üniversitesi",
        "hero_thumbnail": "",
        "slug": "lefkosa-ingiliz-universitesi",
        "university_id": "5616305394679808",
        "is_favourited": false,
        "is_private": true,
        "media_url": "https://storage.googleapis.com/university-images-prod/"
      },
      {
        "city": "İstanbul",
        "hero": "",
        "name": "Maltepe Üniversitesi",
        "hero_thumbnail": "",
        "slug": "maltepe-universitesi",
        "university_id": "5198490976124928",
        "is_favourited": false,
        "is_private": true,
        "media_url": "https://storage.googleapis.com/university-images-prod/"
      },
      {
        "city": "İstanbul",
        "hero": "",
        "name": "Mef Üniversitesi",
        "hero_thumbnail": "",
        "slug": "mef-universitesi",
        "university_id": "4776278511058944",
        "is_favourited": false,
        "is_private": true,
        "media_url": "https://storage.googleapis.com/university-images-prod/"
      },
      {
        "city": "İstanbul",
        "hero": "",
        "name": "Nişantaşı Üniversitesi",
        "hero_thumbnail": "",
        "slug": "nisantas-universitesi",
        "university_id": "4859841394769920",
        "is_favourited": false,
        "is_private": true,
        "media_url": "https://storage.googleapis.com/university-images-prod/"
      },
      {
        "city": "Kayseri",
        "hero": "",
        "name": "Nuh Naci Yazgan Üniversitesi",
        "hero_thumbnail": "",
        "slug": "nuh-naci-yazgan-universitesi",
        "university_id": "5422791348191232",
        "is_favourited": false,
        "is_private": true,
        "media_url": "https://storage.googleapis.com/university-images-prod/"
      },
      {
        "city": "Bakü (Azerbaycan)",
        "hero": "",
        "name": "Odlar Yurdu Üniversitesi",
        "hero_thumbnail": "",
        "slug": "odlar-yurdu-universitesi",
        "university_id": "5431587441213440",
        "is_favourited": false,
        "is_private": true,
        "media_url": "https://storage.googleapis.com/university-images-prod/"
      },
      {
        "city": "İstanbul",
        "hero": "",
        "name": "Okan Üniversitesi",
        "hero_thumbnail": "",
        "slug": "okan-universitesi",
        "university_id": "4719103906414592",
        "is_favourited": false,
        "is_private": true,
        "media_url": "https://storage.googleapis.com/university-images-prod/"
      },
      {
        "city": "İstanbul",
        "hero": "",
        "name": "Özyeğin Üniversitesi",
        "hero_thumbnail": "",
        "slug": "ozyegin-universitesi",
        "university_id": "5106131999391744",
        "is_favourited": false,
        "is_private": true,
        "media_url": "https://storage.googleapis.com/university-images-prod/"
      },
      {
        "city": "İstanbul",
        "hero": "",
        "name": "Piri Reis Üniversitesi",
        "hero_thumbnail": "",
        "slug": "piri-reis-universitesi",
        "university_id": "5387606976102400",
        "is_favourited": false,
        "is_private": true,
        "media_url": "https://storage.googleapis.com/university-images-prod/"
      },
      {
        "city": "İstanbul",
        "hero": "",
        "name": "Sabancı Üniversitesi",
        "hero_thumbnail": "",
        "slug": "sabanc-universitesi",
        "university_id": "5246869487747072",
        "is_favourited": false,
        "is_private": true,
        "media_url": "https://storage.googleapis.com/university-images-prod/"
      },
      {
        "city": "Gaziantep",
        "hero": "",
        "name": "Sanko Üniversitesi",
        "hero_thumbnail": "",
        "slug": "sanko-universitesi",
        "university_id": "5528344464457728",
        "is_favourited": false,
        "is_private": true,
        "media_url": "https://storage.googleapis.com/university-images-prod/"
      },
      {
        "city": "Saraybosna (Bosna-Hersek)",
        "hero": "",
        "name": "Saraybosna Bilim Ve Teknoloji Üniversitesi",
        "hero_thumbnail": "",
        "slug": "saraybosna-bilim-ve-teknoloji-universitesi",
        "university_id": "5290849952858112",
        "is_favourited": false,
        "is_private": true,
        "media_url": "https://storage.googleapis.com/university-images-prod/"
      },
      {
        "city": "Ankara",
        "hero": "",
        "name": "Ted Üniversitesi",
        "hero_thumbnail": "",
        "slug": "ted-universitesi",
        "university_id": "4525589859926016",
        "is_favourited": false,
        "is_private": true,
        "media_url": "https://storage.googleapis.com/university-images-prod/"
      },
      {
        "city": "Ankara",
        "hero": "",
        "name": "Tobb Ekonomi Ve Teknoloji Üniversitesi",
        "hero_thumbnail": "",
        "slug": "tobb-ekonomi-ve-teknoloji-universitesi",
        "university_id": "5088539813347328",
        "is_favourited": false,
        "is_private": true,
        "media_url": "https://storage.googleapis.com/university-images-prod/"
      },
      {
        "city": "Mersin",
        "hero": "",
        "name": "Toros Üniversitesi",
        "hero_thumbnail": "",
        "slug": "toros-universitesi",
        "university_id": "4807064836636672",
        "is_favourited": false,
        "is_private": true,
        "media_url": "https://storage.googleapis.com/university-images-prod/"
      },
      {
        "city": "Ankara",
        "hero": "",
        "name": "Türk Hava Kurumu Üniversitesi",
        "hero_thumbnail": "",
        "slug": "turk-hava-kurumu-universitesi",
        "university_id": "4947802324992000",
        "is_favourited": false,
        "is_private": true,
        "media_url": "https://storage.googleapis.com/university-images-prod/"
      },
      {
        "city": "Ankara",
        "hero": "",
        "name": "Ufuk Üniversitesi",
        "hero_thumbnail": "",
        "slug": "ufuk-universitesi",
        "university_id": "4595958604103680",
        "is_favourited": false,
        "is_private": true,
        "media_url": "https://storage.googleapis.com/university-images-prod/"
      },
      {
        "city": "Antalya",
        "hero": "",
        "name": "Uluslararası Antalya Üniversitesi",
        "hero_thumbnail": "",
        "slug": "uluslararas-antalya-universitesi",
        "university_id": "4877433580814336",
        "is_favourited": false,
        "is_private": true,
        "media_url": "https://storage.googleapis.com/university-images-prod/"
      },
      {
        "city": "Üsküp (Makedonya)",
        "hero": "",
        "name": "Uluslararası Balkan Üniversitesi",
        "hero_thumbnail": "",
        "slug": "uluslararas-balkan-universitesi",
        "university_id": "5114928092413952",
        "is_favourited": false,
        "is_private": true,
        "media_url": "https://storage.googleapis.com/university-images-prod/"
      },
      {
        "city": "Lefkoşa (KKTC)",
        "hero": "",
        "name": "Uluslararası Kıbrıs Üniversitesi",
        "hero_thumbnail": "",
        "slug": "uluslararas-kbrs-universitesi",
        "university_id": "4516793766903808",
        "is_favourited": false,
        "is_private": true,
        "media_url": "https://storage.googleapis.com/university-images-prod/"
      },
      {
        "city": "Saraybosna (Bosna-Hersek)",
        "hero": "",
        "name": "Uluslararası Saraybosna Üniversitesi",
        "hero_thumbnail": "",
        "slug": "uluslararas-saraybosna-universitesi",
        "university_id": "5009374976147456",
        "is_favourited": false,
        "is_private": true,
        "media_url": "https://storage.googleapis.com/university-images-prod/"
      },
      {
        "city": "İstanbul",
        "hero": "",
        "name": "Üsküdar Üniversitesi",
        "hero_thumbnail": "",
        "slug": "uskudar-universitesi",
        "university_id": "4736696092459008",
        "is_favourited": false,
        "is_private": true,
        "media_url": "https://storage.googleapis.com/university-images-prod/"
      },
      {
        "city": "Lefkoşa (KKTC)",
        "hero": "",
        "name": "Yakın Doğu Üniversitesi",
        "hero_thumbnail": "",
        "slug": "yakn-dogu-universitesi",
        "university_id": "5079743720325120",
        "is_favourited": false,
        "is_private": true,
        "media_url": "https://storage.googleapis.com/university-images-prod/"
      },
      {
        "city": "İzmir",
        "hero": "",
        "name": "Yaşar Üniversitesi",
        "hero_thumbnail": "",
        "slug": "yasar-universitesi",
        "university_id": "5018171069169664",
        "is_favourited": false,
        "is_private": true,
        "media_url": "https://storage.googleapis.com/university-images-prod/"
      },
      {
        "city": "İstanbul",
        "hero": "",
        "name": "Yeditepe Üniversitesi",
        "hero_thumbnail": "",
        "slug": "yeditepe-universitesi",
        "university_id": "5581121022590976",
        "is_favourited": false,
        "is_private": true,
        "media_url": "https://storage.googleapis.com/university-images-prod/"
      },
      {
        "city": "İstanbul",
        "hero": "",
        "name": "Yeni Yüzyıl Üniversitesi",
        "hero_thumbnail": "",
        "slug": "yeni-yuzyl-universitesi",
        "university_id": "4560774232014848",
        "is_favourited": false,
        "is_private": true,
        "media_url": "https://storage.googleapis.com/university-images-prod/"
      },
      {
        "city": "Ankara",
        "hero": "",
        "name": "Yüksek İhtisas Üniversitesi",
        "hero_thumbnail": "",
        "slug": "yuksek-ihtisas-universitesi",
        "university_id": "5405199162146816",
        "is_favourited": false,
        "is_private": true,
        "media_url": "https://storage.googleapis.com/university-images-prod/"
      }
    ]
  }
}